[{"model": "MCQAssignmentsApp.youtubevideo", "pk": 1, "fields": {"link": "https://www.youtube.com/embed/Wa58Jt9eQts", "name": "Cat Attacks Ross"}}, {"model": "MCQAssignmentsApp.youtubevideo", "pk": 2, "fields": {"link": "https://www.youtube.com/embed/arlawWou2BU", "name": "Chandler in a Box"}}, {"model": "MCQAssignmentsApp.youtubevideo", "pk": 3, "fields": {"link": "https://www.youtube.com/embed/l9FG4kg8HNU", "name": "Ross's Sandwich"}}, {"model": "MCQAssignmentsApp.youtubevideo", "pk": 4, "fields": {"link": "https://www.youtube.com/embed/R2u0sN9stbA", "name": "Couch Pivot"}}, {"model": "MCQAssignmentsApp.youtubevideo", "pk": 5, "fields": {"link": "https://www.youtube.com/embed/rYe7JECvr30", "name": "Ross Teeth"}}, {"model": "MCQAssignmentsApp.youtubevideo", "pk": 6, "fields": {"link": "https://www.youtube.com/embed/HK-6H79JOxc", "name": "Chesse Cake"}}, {"model": "MCQAssignmentsApp.youtubevideo", "pk": 7, "fields": {"link": "https://www.youtube.com/embed/F7G-LSN9vCs", "name": "Joey Learns French"}}]